allinsso/__init__.py
allinsso/app.py
allinsso/discordoauth.py
allinsso/static/images/allin_official.png
allinsso/static/images/discord-logo-white.svg
allinsso/static/styles/main.css
allinsso/templates/index.html.j2
allinsso-0.0.6.dist-info/METADATA
allinsso-0.0.6.dist-info/RECORD
allinsso-0.0.6.dist-info/WHEEL
allinsso-0.0.6.dist-info/top_level.txt
